beekeeper/readers/file/__init__.py
beekeeper/readers/file/docx.py
beekeeper/readers/file/html.py
beekeeper/readers/file/json.py
beekeeper/readers/file/pdf.py
beekeeper_readers_file-1.0.1.dist-info/METADATA
beekeeper_readers_file-1.0.1.dist-info/WHEEL
beekeeper_readers_file-1.0.1.dist-info/RECORD
