Metadata-Version: 2.4
Name: beekeeper-readers-file
Version: 1.0.1
Summary: beekeeper readers file extension
Author-email: Leonardo Furnielis <leonardofurnielis@outlook.com>
License: Apache-2.0
Requires-Python: <4.0,>=3.10
Requires-Dist: beautifulsoup4<5.0.0,>=4.13.4
Requires-Dist: beekeeper-core<2.0.0,>=1.0.0
Requires-Dist: docx2txt<1.0.0,>=0.9
Requires-Dist: jq<2.0.0,>=1.9.1
Requires-Dist: pypdf<6.0.0,>=5.6.0
Provides-Extra: dev
Requires-Dist: ruff>=0.11.13; extra == 'dev'
